{
  "schema_version": "reaction-remix.proposed.v1",
  "source_hash": "sha256:source",
  "script_hash": "sha256:script",
  "voice_policy": {
    "provider": "ai33",
    "voice_id": "elevenlabs_QPtBgsg1dxKTQHNpHrHt",
    "model": "eleven_multilingual_v2",
    "speed": 1.0,
    "fallback_provider": null,
    "text_normalization": "basic"
  },
  "items": [
    {
      "slot_id": "commentary-slot-0001",
      "audio_path": "audio/commentary-slot-0001.mp3",
      "duration_s": 9.44,
      "provider": "ai33",
      "voice_id": "elevenlabs_QPtBgsg1dxKTQHNpHrHt",
      "model": "eleven_multilingual_v2",
      "speed": 1.0,
      "text_hash": "sha256:text",
      "cache_key": "sha256:cache",
      "normalized": true,
      "lufs_i": -13.5,
      "true_peak_dbfs": -1.7,
      "asr_text_match": 0.96,
      "warnings": []
    }
  ],
  "total_commentary_duration_s": 9.44,
  "created_at": "2026-07-13T12:50:00Z",
  "warnings": []
}
